{
  "_fv": 60,
  "_type": "animatedarmor",
  "definition": {
    "enableHelmet": true,
    "textureHelmet": "arimareglasses",
    "enableBody": true,
    "textureBody": "arimaoektorso",
    "enableLeggings": true,
    "textureLeggings": "arimaoeklegs",
    "enableBoots": true,
    "textureBoots": "arimarefeet",
    "creativeTab": {
      "value": "COMBAT"
    },
    "armorTextureFile": "arimaoekoutfit.png",
    "model": "arimaoekoutfit.geo.json",
    "idle": "animation.arimaoekoutfit.idle",
    "head": "armorHead",
    "chest": "armorBody",
    "rightArm": "armorRightArm",
    "leftArm": "armorLeftArm",
    "rightLeg": "armorRightLeg",
    "leftLeg": "armorLeftLeg",
    "rightBoot": "armorRightBoot",
    "leftBoot": "armorLeftBoot",
    "helmetName": "One Eyed King's Glasses",
    "bodyName": "One Eyed King's Coat",
    "leggingsName": "One Eyed King's Pants",
    "bootsName": "One Eyed King's Loafers",
    "helmetSpecialInfo": [],
    "bodySpecialInfo": [],
    "leggingsSpecialInfo": [],
    "bootsSpecialInfo": [],
    "helmetItemRenderType": 0,
    "helmetItemCustomModelName": "Normal",
    "bodyItemRenderType": 0,
    "bodyItemCustomModelName": "Normal",
    "leggingsItemRenderType": 0,
    "leggingsItemCustomModelName": "Normal",
    "bootsItemRenderType": 0,
    "bootsItemCustomModelName": "Normal",
    "helmetImmuneToFire": false,
    "bodyImmuneToFire": false,
    "leggingsImmuneToFire": false,
    "bootsImmuneToFire": false,
    "fullyEquipped": false,
    "maxDamage": 25,
    "damageValueHelmet": 2,
    "damageValueBody": 6,
    "damageValueLeggings": 5,
    "damageValueBoots": 2,
    "enchantability": 0,
    "toughness": 0.0,
    "knockbackResistance": 0.0,
    "equipSound": {
      "value": "item.armor.equip_leather"
    },
    "repairItems": []
  }
}